csv_object_reader/__init__.py
csv_object_reader/object_reader.py
csv_object_reader-0.1.1.dist-info/DESCRIPTION.rst
csv_object_reader-0.1.1.dist-info/metadata.json
csv_object_reader-0.1.1.dist-info/top_level.txt
csv_object_reader-0.1.1.dist-info/METADATA
csv_object_reader-0.1.1.dist-info/RECORD
csv_object_reader-0.1.1.dist-info/WHEEL
