Metadata-Version: 2.0
Name: csv-object-reader
Version: 0.1.1
Summary: CSV file reader which returns objects
Home-page: https://github.com/fireyone29/csv_object_reader
Author: fireyone29
Author-email: fireyone29@gmail.com
License: MIT
Keywords: csv_object_reader,csv
Platform: UNKNOWN
Classifier: Development Status :: 2 - Pre-Alpha
Classifier: Intended Audience :: Developers
Classifier: License :: OSI Approved :: MIT License
Classifier: Natural Language :: English
Classifier: Programming Language :: Python :: 2
Classifier: Programming Language :: Python :: 2.7
Classifier: Programming Language :: Python :: 3
Classifier: Programming Language :: Python :: 3.3
Classifier: Programming Language :: Python :: 3.4
